smocktools/__init__.py
smocktools/mysqlRepository.py
smocktools-0.1.3.dist-info/LICENSE.txt
smocktools-0.1.3.dist-info/METADATA
smocktools-0.1.3.dist-info/WHEEL
smocktools-0.1.3.dist-info/top_level.txt
smocktools-0.1.3.dist-info/RECORD
