Metadata-Version: 2.1
Name: smocktools
Version: 0.1.3
Summary: A package
Home-page: https://github.com/smockgithub/smocktools
Author: smock
Author-email: smockg@gmail.com
License: UNKNOWN
Platform: UNKNOWN
Classifier: Programming Language :: Python :: 3
Classifier: License :: OSI Approved :: MIT License
Classifier: Operating System :: OS Independent
Requires-Python: >=3
License-File: LICENSE.txt
Requires-Dist: sshtunnel
Requires-Dist: pymysql
